pymesomb/__init__.py
pymesomb/exceptions.py
pymesomb/mesomb.py
pymesomb/models.py
pymesomb/operations.py
pymesomb/signature.py
pymesomb/utils.py
pymesomb-2.0.3.dist-info/LICENSE
pymesomb-2.0.3.dist-info/METADATA
pymesomb-2.0.3.dist-info/WHEEL
pymesomb-2.0.3.dist-info/top_level.txt
pymesomb-2.0.3.dist-info/RECORD
