Metadata-Version: 2.1
Name: pymesomb
Version: 2.0.3
Summary: Python client for MeSomb services.
Home-page: https://github.com/hachther/mesomb-python-client.git
Download-URL: https://pypi.org/project/pymesomb/
Author: Hachther LLC
Author-email: contact@hachther.com
License: MIT
Keywords: MeSomb,MobileMoney,OrangeMoney,YangoRefill
Classifier: Development Status :: 5 - Production/Stable
Classifier: Intended Audience :: Developers
Classifier: License :: OSI Approved :: MIT License
Classifier: Natural Language :: English
Classifier: Programming Language :: Python :: 3
Classifier: Programming Language :: Python :: 3.6
Classifier: Programming Language :: Python :: 3.7
Classifier: Programming Language :: Python :: 3.8
Classifier: Programming Language :: Python :: 3.9
Classifier: Programming Language :: Python :: 3.10
Classifier: Programming Language :: Python :: 3.11
Classifier: Programming Language :: Python :: 3.12
Classifier: Programming Language :: Python :: 3.13
License-File: LICENSE
Requires-Dist: requests
